thonnycontrib/struktog/__init__.py
thonny_struktog_test-0.0.2.dist-info/LICENSE
thonny_struktog_test-0.0.2.dist-info/METADATA
thonny_struktog_test-0.0.2.dist-info/WHEEL
thonny_struktog_test-0.0.2.dist-info/top_level.txt
thonny_struktog_test-0.0.2.dist-info/RECORD
