Metadata-Version: 2.1
Name: thonny-struktog-test
Version: 0.0.2
Summary: Struktog webdriver client plugin for thonny
Home-page: https://github.com/DDI-TU-Dresden/thonny-webdriver/tree/struktog
Author: niklaskeerl
Author-email: niklas.keerl@mailbox.org
License: UNKNOWN
Platform: UNKNOWN
Classifier: Intended Audience :: Education
Classifier: Programming Language :: Python :: 3
Classifier: License :: OSI Approved :: MIT License
Classifier: Operating System :: OS Independent
Classifier: Topic :: Education
Classifier: Topic :: Software Development
Requires-Python: >=3.5
Requires-Dist: thonny
Requires-Dist: selenium
